tscompare/__init__.py
tscompare/_version.py
tscompare/methods.py
tscompare/provenance.py
tscompare-0.2.dist-info/licenses/LICENSE
tscompare-0.2.dist-info/METADATA
tscompare-0.2.dist-info/WHEEL
tscompare-0.2.dist-info/top_level.txt
tscompare-0.2.dist-info/RECORD
